genutcstamp.py
GenUTCStamp/__init__.py
GenUTCStamp/__main__.py
GenUTCStamp/cli.py
genutcstamp-1.0.3.dist-info/licenses/LICENSE
genutcstamp-1.0.3.dist-info/METADATA
genutcstamp-1.0.3.dist-info/WHEEL
genutcstamp-1.0.3.dist-info/top_level.txt
genutcstamp-1.0.3.dist-info/RECORD
