Metadata-Version: 2.4
Name: GenUTCStamp
Version: 1.0.3
Summary: Dependency-free UTC timestamp string generation helper (YYYY-MM-DDTHH:MM:SSZ).
Author: Marcin Kowalczyk
License: MIT
Project-URL: Homepage, https://pypi.org/project/GenUTCStamp/
Keywords: utc,timestamp,rfc3339,iso8601,logging
Requires-Python: >=3.9
License-File: LICENSE
Dynamic: license-file
